dagpipe/__init__.py
dagpipe/errors.py
dagpipe/pipeline.py
dagpipe/task_core.py
dagpipe/task_decorators.py
dagpipe/task_params.py
dagpipe/typing.py
dagpipe/utils.py
dagpipe/visualization.py
dagpipe-0.2.21.dist-info/LICENCE
dagpipe-0.2.21.dist-info/METADATA
dagpipe-0.2.21.dist-info/WHEEL
dagpipe-0.2.21.dist-info/top_level.txt
dagpipe-0.2.21.dist-info/RECORD
