Metadata-Version: 2.1
Name: dagpipe
Version: 0.2.21
Summary: Package that allows user to define lazy evaluated dag pipeline.
Home-page: https://github.com/WojciechBogobowicz/dagpipe
Author: Wojciech Bogobowicz
Author-email: wojciech.bogobowicz@gmail.com
Classifier: Programming Language :: Python :: 3
Classifier: License :: OSI Approved :: MIT License
Classifier: Operating System :: OS Independent
Requires-Python: >=3.6
License-File: LICENCE
Provides-Extra: viz
Requires-Dist: graphviz ; extra == 'viz'
Requires-Dist: matplotlib ; extra == 'viz'
